多周期cpu/alu.v
module ALU(input [31:0] A,input [31:0] B,input [2:0] alu_ctrl,input ALUOe,output [31:0] alu_out_real,output Z);
    reg [31:0] C; 
    reg [32:0] C_with_Z;
    reg [31:0] alu_out_real;
    reg Z;
    always@(*)begin
        Z=0;
        case(alu_ctrl)
            3'b100:begin 
                C_with_Z=A+B;
                C=C_with_Z[31:0];
                Z=C_with_Z[32];
            end
            3'b110:begin
                C_with_Z=A-B;
                C=C_with_Z[31:0];
                Z=(A<B);
            end
            3'b101:C=A+B;
            3'b000:C=A&B;
            3'b001:C=A|B;
            3'b011:C=A^B;
            3'b010:begin
                if(A<B) begin
                    C=33'b00000000000000000000000000000001;
                end
                else begin
                    C=33'b00000000000000000000000000000000;
                end
            end
            3'b111:begin
                if(A==B) begin
                    Z=1'b1;
                end
                else begin
                    Z=1'b0;
                end
            end
        endcase
    end

    always@(posedge ALUOe) begin
        #1
        alu_out_real=C;
    end

    always@(negedge ALUOe) begin
        alu_out_real=32'bz;
    end
endmodule

module ALUCU(input [1:0] alu_op,input [5:0] func_code,output [2:0] alu_ctrl);
    reg [2:0] alu_ctrl;
    always@(*)begin
        case(alu_op)
            2'b00:alu_ctrl=3'b100; //PC+4
            2'b01:alu_ctrl=3'b111; //beq
        endcase
        if(alu_op[1]==1'b1)begin //常规算数指令
            case(func_code)
                6'b100000:alu_ctrl=3'b100; //+(jud)
                6'b100001:alu_ctrl=3'b101; //+
                6'b100010:alu_ctrl=3'b110; //-
                6'b100100:alu_ctrl=3'b000; //&
                6'b100101:alu_ctrl=3'b001; //|
                6'b101010:alu_ctrl=3'b011; //^
                6'b101011:alu_ctrl=3'b010; //A<B->1 else 0
            endcase
        end
    end
endmodule

module ALUsaveA(input AWr,input [31:0] in,output [31:0] out);
    reg [31:0] out; 
    reg [31:0] save;
    always@(posedge AWr) begin
        #2
        out=in;
    end
endmodule

module ALUsaveB(input BWr,input [31:0] in,output [31:0] out);
    reg [31:0] out; 
    reg [31:0] save;
    always@(posedge BWr)begin
        #2
        out=in;
    end
endmodule

多周期cpu/RF.v
module RF(
    input clk,
    input [31:0] RF_Wdata,
    input [4:0] RF_reg,
    input RF_Oe,
    input RF_w,
    output reg [31:0] RF_Rdata);

    reg [31:0] RF_memory[0:31];
    integer j;

    initial begin
        for(j=0; j<=31; j=j+1)begin
            RF_memory[j]=j;
        end
    end

    always@(posedge clk) begin
        #2
        if(RF_w) RF_memory[RF_reg]=RF_Wdata;
        if(RF_Oe) RF_Rdata=RF_memory[RF_reg];
    end

    always@(negedge RF_Oe) begin
        RF_Rdata=32'bz;
    end
endmodule

多周期cpu/mux.v
module mux_DM(input [31:0] mux_in1,input clk,input [31:0] mux_in2,input mux_ctrl,output [31:0] mux_out);
    reg [31:0] mux_out;
    always@(posedge clk)begin
        #3
        case(mux_ctrl)
            1'b1:mux_out=mux_in2;
            1'b0:mux_out=mux_in1;
        endcase
    end
endmodule

module mux_reg(input [4:0] mux_in1,input [4:0] mux_in2,input [4:0] mux_in3,input [1:0] mux_ctrl,output [4:0] mux_out);
    reg [4:0] mux_out;
    always@(*)begin
        case(mux_ctrl)
            2'b00:mux_out=mux_in1;
            2'b01:mux_out=mux_in2;
            2'b10:mux_out=mux_in3;
        endcase
    end
endmodule

多周期cpu/pc.v
module PC(input clk,input PCWr,input PCOeH,input PCOeL,input [31:0] pcin,output reg [31:0] testpc,output [3:0] pcouth,output [27:0] pcoutl);
    reg[31:0] pctemp;
    reg[3:0] pcouth;
    reg[27:0] pcoutl;

    initial begin
        pctemp=32'b0;
    end

    always@(posedge clk)begin
        #2 
        if(PCWr)begin
            pctemp=pcin;
        end
    end

    always@(posedge PCOeH) pcouth=pctemp[31:28];
    always@(posedge PCOeL) pcoutl=pctemp[27:0];
    always@(negedge PCOeH) pcouth=4'bz;
    always@(negedge PCOeL) pcoutl=28'bz;
endmodule

多周期cpu/DM.v
module DM(
    input [31:0] DM_addr,
    input DM_r,
    input DM_w,
    input [31:0] data_write,
    output [31:0] data_read);

    reg [31:0] memory[0:255];
    reg [31:0] data_read;
    integer i;

    initial begin
        memory[0]=32'b00000000000000010001000000100001; //RF[2]=RF[0]+RF[1]=1
        memory[1]=32'b00000000100000110010100001100010; //RF[5]=RF[4]-RF[3]=1
        memory[2]=32'b10001100001001000000000000011000; //DM[24+1](9)->RF[4]=9
        memory[3]=32'b10101100010111110000000000001111; //RF[31](31)->DM[15+1]=31 
        memory[4]=32'b00000000000000010011100000101011; //RF[0]<RF[1]?->RF[7]=1(triggered)
        memory[5]=32'b00010000001000100000000000000001; //RF[1]==RF[2]?->PC+=1(triggered)
        memory[6]=32'b10001100100000000000000000000111; //DM[7+9](31)->RF[0]=31(skipped)
        memory[7]=32'b10001100100000000000000000001000; //DM[8+9](1)->RF[0]=1
        memory[8]=32'b00001000000000000000000000000000; //PC=0
                                                        //PC=0 RF[2]=RF[0]+RF[1]=2
                                                        //PC=1 RF[5]=RF[4]-RF[3]=6
                                                        //PC=2 DM[24+1](9)->RF[4]=9
                                                        //PC=3 RF[31](31)->DM[15+2]=31
                                                        //PC=4 RF[0]<RF[1]?->RF[7]=1(not triggered)
                                                        //PC=5 RF[1]==RF[2]?->PC+=1(not triggered)
                                                        //PC=6 DM[7+9](31)->RF[0]=31
                                                        //PC=7 DM[8+9](31)->RF[0]=31

        for(i=16;i<=31;i=i+1) begin
            memory[i]=i-16;
        end
    end

    always@(posedge DM_r) begin
        data_read=memory[DM_addr[7:0]];
    end

    always@(posedge DM_w) begin
        memory[DM_addr[7:0]]=data_write;
    end
endmodule

module DM_out_ctrl(input MemOe,input [31:0] in,output [31:0] out);
    reg [31:0] out;
    reg [31:0] save;

    always@(*) begin
        save=in;
    end

    always@(posedge MemOe) begin
        #1
        out=save; 
    end

    always@(negedge MemOe) out=32'bz;
endmodule

module MAR(input clk,input [31:0] MAR_IN,input MARWr,output [31:0] MAR_OUT);
    reg [31:0] MAR_OUT;
    reg [31:0] save;

    always@(*) begin
        save=MAR_IN;
    end

    always@(posedge clk) begin
        #2
        if(MARWr) MAR_OUT=MAR_IN;
    end
endmodule

module MDR(input clk,input [31:0] MDR_IN,input MDRWr,output [31:0] MDR_OUT);
    reg [31:0] MDR_OUT;
    reg [31:0] save;

    always@(*) begin
        save=MDR_IN;
    end

    always@(posedge clk) begin
        #4
        if(MDRWr) begin
            MDR_OUT=MDR_IN;
        end
    end
endmodule

module MDR_out_ctrl(input MDROe,input [31:0] in,output [31:0] out);
    reg [31:0] out;
    reg [31:0] save;

    always@(*) save=in;
    always@(posedge MDROe) out=save;
    always@(negedge MDROe) out=32'bz;
endmodule

多周期cpu/sigExt.v
module sigext(input [31:0] in,input [1:0] extsel,input ImmOeH,input ImmOeL,output reg [3:0] out4,output reg [27:0] out28);
    reg [31:0] out;
    always@(*)begin
        case(extsel)
            2'b10:begin
                out=32'h00000001;
            end
            2'b11:begin
                out[31:26]=6'b0;
                out[25:0]=in[25:0];
                //out=out<<2;
            end
            default begin
                out[15:0]=in[15:0];
                case(in[15])
                    1'b1:out[31:16]=16'hffff;
                    1'b0:out[31:16]=16'h0;
                endcase
                //if(extsel[0]) out=out<<2;
            end
        endcase
    end

    always@(posedge ImmOeH) begin
        out4=out[31:28];
    end

    always@(posedge ImmOeL) begin 
        out28=out[27:0];
    end

    always@(negedge ImmOeH) begin 
        out4=4'bz;
    end

    always@(negedge ImmOeL) begin 
        out28=28'bz;
    end
endmodule

多周期cpu/IR.v
module IR(input clk,input IRWr,input [31:0] IR_in,output reg [31:0] IRout);//,output reg [4:0] IRreg1,output reg [4:0] IRreg2,output reg [4:0] IRreg3,output reg [5:0] IR_ALUfunc);
    always@(posedge clk) begin
        #2 
        if(IRWr)begin
            IRout=IR_in;
            //IRreg1=IR_in[25:21];
            //IRreg2=IR_in[20:16];
            //IRreg3=IR_in[15:11];
            //IR_ALUfunc=IR_in[5:0];
        end
    end
endmodule

多周期cpu/MCU.v
module CU(
    input clk,
    input [31:0] MCU_in,
    input ALU_Z,
    output reg PCOeH,
    output reg PCOeL,
    output reg PCWr,
    output reg IRWr,
    output reg ImmOeH,
    output reg ImmOeL,
    output reg [1:0] ExtSel,
    output reg [1:0] ALUOp,
    //output reg [2:0] ALUCtrl,
    output reg AWr,
    output reg BWr,
    output reg ALUOe,
    output reg RegOe,
    output reg RegWr,
    output reg [1:0] RegSel,
    output reg MARWr,
    output reg MemRd,
    output reg MemWr,
    output reg MDRSrc,
    output reg MDROe,
    output reg MDRWr,
    output reg MemOe);
    
    integer period=0; //clock period
    integer ex=0;
    reg [31:0] OP_code;

always@(posedge clk)begin
    case(period)
        0:begin
            PCOeH=1;
            PCOeL=1;
            MARWr=1;
            AWr=1;
            period=period+1;
        end
        1:begin
            MemRd=1;
            MemOe=1;
            IRWr=1;
            period=period+1;
            #2
            OP_code=MCU_in;
        end
        2:begin
            ExtSel=2'b10;
            ImmOeH=1;
            ImmOeL=1;
            BWr=1;
            period=period+1;
        end
        3:begin
            ALUOp=2'b00;
            ALUOe=1;
            PCWr=1;
            period=period+1;
        end
        4:begin
            RegSel=00;
            RegOe=1;
            AWr=1;
            period=period+1;
        end
        5:begin
            case(OP_code[31:26])
                6'b100011:begin //lw
                    ExtSel=2'b00;
                    ImmOeH=1;
                    ImmOeL=1;
                    BWr=1;
                    period=period+1;
                end
                6'b101011:begin //sw
                    ExtSel=2'b00;
                    ImmOeH=1;
                    ImmOeL=1;
                    BWr=1;
                    period=period+1;
                end
                6'b000000:begin //R
                    RegSel=2'b01;
                    RegOe=1;
                    BWr=1;
                    period=period+1;
                end
                6'b000100:begin //beq
                    RegSel=2'b01;
                    RegOe=1;
                    BWr=1;
                    period=period+1;
                end
                6'b000010:begin //j
                    PCOeH=1;
                    ExtSel=2'b11;
                    ImmOeL=1;
                    PCWr=1;
                    OP_code=0;
                    period=0;
                end
            endcase
        end
        6:begin
            case(OP_code[31:26])
                6'b100011:begin //lw
                    ALUOp=2'b00;
                    //ALUCtrl=3'b100;
                    ALUOe=1;
                    MARWr=1;
                    period=period+1;
                end
                6'b101011:begin //sw
                    ALUOp=2'b00;
                    //ALUCtrl=3'b100;
                    ALUOe=1;
                    MARWr=1;
                    period=period+1;
                end
                6'b000000:begin //R
                    ALUOp=2'b10;
                    ALUOe=1;
                    RegSel=2'b10;
                    RegWr=1;
                    OP_code=0;
                    period=0;
                end
                6'b000100:begin //beq
                    ALUOp=2'b01;
                    #2
                    if(ALU_Z==0)begin
                        OP_code=0;
                        period=0;
                    end
                    else begin
                        PCOeH=1;
                        PCOeL=1;
                        AWr=1;
                        period=period+1;
                    end
                end
            endcase
        end
        7:begin
            case(OP_code[31:26])
                6'b100011:begin //lw
                    MemRd=1;
                    MDRSrc=1;
                    MDRWr=1;
                    period=period+1;
                end
                6'b101011:begin //sw
                    RegSel=2'b01;
                    RegOe=1;
                    MDRSrc=0;
                    MDRWr=1;
                    period=period+1;
                end
                6'b000100:begin //beq
                    ExtSel=2'b01;
                    ImmOeH=1;
                    ImmOeL=1;
                    BWr=1;
                    period=period+1;
                end
            endcase
        end
        8:begin
            case(OP_code[31:26])
                6'b100011:begin //lw
                    MDROe=1;
                    RegSel=2'b01;
                    RegWr=1;
                    OP_code=0;
                    period=0;
                end
                6'b101011:begin //sw
                    MemWr=1;
                    OP_code=0;
                    period=0;
                end
                6'b000100:begin //beq
                    ALUOp=2'b00;
                    //ALUCtrl=3'b100;
                    ALUOe=1;
                    PCWr=1;
                    OP_code=0;
                    period=0;
                end
            endcase
        end
    endcase
end

always@(negedge clk)begin
    PCOeH=0;
    PCOeL=0;
    PCWr=0;
    IRWr=0;
    ImmOeH=0;
    ImmOeL=0;
    ExtSel=0;
    ALUOp=0;
    //ALUCtrl=0;
    AWr=0;
    BWr=0;
    ALUOe=0;
    RegOe=0;
    RegWr=0;
    RegSel=0;
    MARWr=0;
    MemRd=0;
    MemWr=0;
    MDRSrc=0;
    MDROe=0;
    MDRWr=0;
    MemOe=0;
end
endmodule

多周期cpu/cpu.v
//I型指令
//lw 100011(6) + Rs(5) + Rt(5) + Imm16
//rw 101011(6) + Rs(5) + Rt(5) + Imm16
//beq 000100(6) + Rs(5) + Rt(5) + Addr16
//R型指令
//000000(6) + Rd(5) + Rs(5) + Rt(5) + empty(5) + func(6)
//func
//100000 alu_ctrl=3'b100; //+(jud)
//100001 alu_ctrl=3'b101; //+
//100010 alu_ctrl=3'b110; //-
//100100 alu_ctrl=3'b000; //&
//100101 alu_ctrl=3'b001; //|
//101010 alu_ctrl=3'b011; //^
//101011 alu_ctrl=3'b010; //A<B->1 else 0
//J型指令
//000010(6) + Addr26
`timescale 1ns/1ns
`include "alu.v"
`include "DM.v"
`include "MCU.v"
`include "pc.v"
`include "RF.v"
`include "IR.v"
`include "mux.v"
`include "sigExt.v"

module cpu; 
    reg clk;
    tri [31:0] Bus;
    wire [31:0] ctrl_wire;
    wire [31:0] data_wire [0:31];
    wire [5:0] alu_func_code;
    wire [4:0] RF_reg [0:10];
    reg [3:0] qq;
    reg [3:0] pp;
    integer i,j;
    CU my_CU(
        .clk(clk),
        .MCU_in(data_wire[0]),
        .ALU_Z(ctrl_wire[5]),
        .PCOeH(ctrl_wire[31]),
        .PCOeL(ctrl_wire[30]),
        .PCWr(ctrl_wire[29]),
        .IRWr(ctrl_wire[28]),
        .ImmOeH(ctrl_wire[27]),
        .ImmOeL(ctrl_wire[26]),
        .ExtSel(ctrl_wire[4:3]),
        .ALUOp(ctrl_wire[24:23]),
        //.ALUCtrl(ctrl_wire[22:20]),
        .AWr(ctrl_wire[19]),
        .BWr(ctrl_wire[18]),
        .ALUOe(ctrl_wire[17]),
        .RegOe(ctrl_wire[16]),
        .RegWr(ctrl_wire[15]),
        .RegSel(ctrl_wire[14:13]),
        .MARWr(ctrl_wire[12]),
        .MemRd(ctrl_wire[11]),
        .MemWr(ctrl_wire[10]),
        .MDRSrc(ctrl_wire[9]),
        .MDROe(ctrl_wire[8]),
        .MDRWr(ctrl_wire[7]),
        .MemOe(ctrl_wire[6])
    );

    IR my_IR(
        .clk(clk),
        .IRWr(ctrl_wire[28]),
        .IR_in(Bus),
        .IRout(data_wire[0])
        //.IRreg1(RF_reg[0]),
        //.IRreg2(RF_reg[1]),
        //.IRreg3(RF_reg[2]),
        //.IR_ALUfunc(alu_func_code)
    );

    sigext my_sigext(
        .in(data_wire[0]),
        .extsel(ctrl_wire[4:3]),
        .ImmOeH(ctrl_wire[27]),
        .ImmOeL(ctrl_wire[26]),
        .out4(Bus[31:28]),
        .out28(Bus[27:0])
    );

    mux_DM my_mux_DM(
        .clk(clk),
        .mux_in1(Bus),
        .mux_in2(data_wire[5]),
        .mux_ctrl(ctrl_wire[9]),
        .mux_out(data_wire[6])
    );
    
    MDR_out_ctrl my_MDR_out_ctrl(
        .MDROe(ctrl_wire[8]),
        .in(data_wire[4]),
        .out(Bus)
    );

    DM_out_ctrl my_DM_out_ctrl(
        .MemOe(ctrl_wire[6]),
        .in(data_wire[5]),
        .out(Bus)
    );

    MDR my_MDR(
        .clk(clk),
        .MDR_IN(data_wire[6]),
        .MDRWr(ctrl_wire[7]),
        .MDR_OUT(data_wire[4])
    );

    MAR my_MAR(
        .clk(clk),
        .MAR_IN(Bus),
        .MARWr(ctrl_wire[12]),
        .MAR_OUT(data_wire[3])
    );

    DM my_DM(
        .DM_addr(data_wire[3]),
        .DM_r(ctrl_wire[11]),
        .DM_w(ctrl_wire[10]),
        .data_write(data_wire[4]),
        .data_read(data_wire[5])
    );

    PC my_PC(
        .clk(clk),
        .PCWr(ctrl_wire[29]),
        .PCOeH(ctrl_wire[31]),
        .PCOeL(ctrl_wire[30]),
        .pcin(Bus),
        .pcoutl(Bus[27:0]),
        .pcouth(Bus[31:28])
    );

    mux_reg my_mux_reg(
        .mux_in1(data_wire[0][25:21]),
        .mux_in2(data_wire[0][20:16]),
        .mux_in3(data_wire[0][15:11]),
        .mux_ctrl(ctrl_wire[14:13]),
        .mux_out(RF_reg[3])
    );

    RF my_RF(
        .clk(clk),
        .RF_Wdata(Bus),
        .RF_reg(RF_reg[3]),
        .RF_Oe(ctrl_wire[16]),
        .RF_w(ctrl_wire[15]),
        .RF_Rdata(Bus)
    );

    ALU my_ALU(
        .A(data_wire[1]),
        .B(data_wire[2]),
        .alu_ctrl(ctrl_wire[22:20]),
        .ALUOe(ctrl_wire[17]),
        .alu_out_real(Bus),
        .Z(ctrl_wire[5])
    );

    ALUCU my_ALUCU(
        .alu_op(ctrl_wire[24:23]),
        .func_code(data_wire[0][5:0]),
        .alu_ctrl(ctrl_wire[22:20])
    );

    ALUsaveA my_ALUsaveA(
        .AWr(ctrl_wire[19]),
        .in(Bus),
        .out(data_wire[1])
    );

    ALUsaveB my_ALUsaveB(
        .BWr(ctrl_wire[18]),
        .in(Bus),
        .out(data_wire[2])
    );

    initial begin
        clk=0;
    end

    always begin
        if(my_CU.period==0) begin
            $display("----------");
            $write("reg[0-7]");
            for(i=0;i<=7;i=i+1) begin
                $write(my_RF.RF_memory[i]);
            end
            $display(" ");
            $write("dm[16-23]");
            for(i=16;i<=23;i=i+1) begin
                $write(my_DM.memory[i]);
            end
            $display(" ");
        end
        #8 clk=~clk;
        #8 clk=~clk;
    end

    initial begin
        #2100 $finish;
    end

    initial begin            
        $dumpfile("wave.vcd");
        $dumpvars(0,cpu);
    end 
endmodule

多周期cpu/wave.vcd
$date
	Sun Feb 26 16:19:43 2023
$end
$version
	Icarus Verilog
$end
$timescale
	1ns
$end
$scope module cpu $end
$var wire 32 ! Bus [31:0] $end
$var wire 32 " ctrl_wire [31:0] $end
$var reg 1 # clk $end
$var integer 32 $ i [31:0] $end
$scope module my_ALU $end
$var wire 1 % ALUOe $end
$var wire 3 & alu_ctrl [2:0] $end
$var wire 32 ' B [31:0] $end
$var wire 32 ( A [31:0] $end
$var reg 32 ) C [31:0] $end
$var reg 33 * C_with_Z [32:0] $end
$var reg 1 + Z $end
$var reg 32 , alu_out_real [31:0] $end
$upscope $end
$scope module my_ALUCU $end
$var wire 2 - alu_op [1:0] $end
$var wire 6 . func_code [5:0] $end
$var reg 3 / alu_ctrl [2:0] $end
$upscope $end
$scope module my_ALUsaveA $end
$var wire 1 0 AWr $end
$var wire 32 1 in [31:0] $end
$var reg 32 2 out [31:0] $end
$upscope $end
$scope module my_ALUsaveB $end
$var wire 1 3 BWr $end
$var wire 32 4 in [31:0] $end
$var reg 32 5 out [31:0] $end
$upscope $end
$scope module my_CU $end
$var wire 1 6 ALU_Z $end
$var wire 1 # clk $end
$var wire 32 7 MCU_in [31:0] $end
$var reg 1 8 ALUOe $end
$var reg 2 9 ALUOp [1:0] $end
$var reg 1 : AWr $end
$var reg 1 ; BWr $end
$var reg 2 < ExtSel [1:0] $end
$var reg 1 = IRWr $end
$var reg 1 > ImmOeH $end
$var reg 1 ? ImmOeL $end
$var reg 1 @ MARWr $end
$var reg 1 A MDROe $end
$var reg 1 B MDRSrc $end
$var reg 1 C MDRWr $end
$var reg 1 D MemOe $end
$var reg 1 E MemRd $end
$var reg 1 F MemWr $end
$var reg 32 G OP_code [31:0] $end
$var reg 1 H PCOeH $end
$var reg 1 I PCOeL $end
$var reg 1 J PCWr $end
$var reg 1 K RegOe $end
$var reg 2 L RegSel [1:0] $end
$var reg 1 M RegWr $end
$var integer 32 N ex [31:0] $end
$var integer 32 O period [31:0] $end
$upscope $end
$scope module my_DM $end
$var wire 1 P DM_r $end
$var wire 1 Q DM_w $end
$var wire 32 R data_write [31:0] $end
$var wire 32 S DM_addr [31:0] $end
$var reg 32 T data_read [31:0] $end
$var integer 32 U i [31:0] $end
$upscope $end
$scope module my_DM_out_ctrl $end
$var wire 1 V MemOe $end
$var wire 32 W in [31:0] $end
$var reg 32 X out [31:0] $end
$var reg 32 Y save [31:0] $end
$upscope $end
$scope module my_IR $end
$var wire 1 Z IRWr $end
$var wire 32 [ IR_in [31:0] $end
$var wire 1 # clk $end
$var reg 32 \ IRout [31:0] $end
$upscope $end
$scope module my_MAR $end
$var wire 1 ] MARWr $end
$var wire 32 ^ MAR_IN [31:0] $end
$var wire 1 # clk $end
$var reg 32 _ MAR_OUT [31:0] $end
$var reg 32 ` save [31:0] $end
$upscope $end
$scope module my_MDR $end
$var wire 1 a MDRWr $end
$var wire 1 # clk $end
$var wire 32 b MDR_IN [31:0] $end
$var reg 32 c MDR_OUT [31:0] $end
$var reg 32 d save [31:0] $end
$upscope $end
$scope module my_MDR_out_ctrl $end
$var wire 1 e MDROe $end
$var wire 32 f in [31:0] $end
$var reg 32 g out [31:0] $end
$var reg 32 h save [31:0] $end
$upscope $end
$scope module my_PC $end
$var wire 1 i PCOeH $end
$var wire 1 j PCOeL $end
$var wire 1 k PCWr $end
$var wire 1 # clk $end
$var wire 32 l pcin [31:0] $end
$var reg 4 m pcouth [3:0] $end
$var reg 28 n pcoutl [27:0] $end
$var reg 32 o pctemp [31:0] $end
$var reg 32 p testpc [31:0] $end
$upscope $end
$scope module my_RF $end
$var wire 1 q RF_Oe $end
$var wire 32 r RF_Wdata [31:0] $end
$var wire 1 s RF_w $end
$var wire 1 # clk $end
$var wire 5 t RF_reg [4:0] $end
$var reg 32 u RF_Rdata [31:0] $end
$var integer 32 v j [31:0] $end
$upscope $end
$scope module my_mux_DM $end
$var wire 1 # clk $end
$var wire 1 w mux_ctrl $end
$var wire 32 x mux_in1 [31:0] $end
$var wire 32 y mux_in2 [31:0] $end
$var reg 32 z mux_out [31:0] $end
$upscope $end
$scope module my_mux_reg $end
$var wire 2 { mux_ctrl [1:0] $end
$var wire 5 | mux_in1 [4:0] $end
$var wire 5 } mux_in2 [4:0] $end
$var wire 5 ~ mux_in3 [4:0] $end
$var reg 5 !" mux_out [4:0] $end
$upscope $end
$scope module my_sigext $end
$var wire 1 "" ImmOeH $end
$var wire 1 #" ImmOeL $end
$var wire 2 $" extsel [1:0] $end
$var wire 32 %" in [31:0] $end
$var reg 32 &" out [31:0] $end
$var reg 28 '" out28 [27:0] $end
$var reg 4 (" out4 [3:0] $end
$upscope $end
$upscope $end
$enddefinitions $end
$comment Show the parameter values. $end
$dumpall
$end
#0
$dumpvars
bz ("
bz '"
bx &"
bx %"
b0 $"
0#"
0""
bx !"
bx ~
bx }
bx |
b0 {
bx z
bx y
bz x
0w
b100000 v
bz u
bx t
0s
bz r
0q
bx p
b0 o
bz n
bz m
bz l
0k
0j
0i
bx h
bz g
bx f
0e
bx d
bx c
bx b
0a
bz `
bx _
bz ^
0]
bx \
bz [
0Z
bx Y
bz X
bx W
0V
b100000 U
bx T
bx S
bx R
0Q
0P
b0 O
b0 N
0M
b0 L
0K
0J
0I
0H
bx G
0F
0E
0D
0C
0B
0A
0@
0?
0>
0=
b0 <
0;
0:
b0 9
08
bx 7
x6
bx 5
bz 4
03
bx 2
bz 1
00
b100 /
bx .
b0 -
bz ,
x+
bx *
bx )
bx (
bx '
b100 &
0%
b11000 $
0#
b0z0010000000000000000x00zzz "
bz !
$end
#8
b0 n
b0 !
b0 1
b0 4
b0 [
b0 ^
b0 l
b0 r
b0 x
b0 m
10
1]
1j
1i
b1 O
1:
1@
1I
b110000z0010010000001000000x00zzz "
1H
1#
#10
b110000z0010010000001000000x00zzz "
x+
b0 (
b0 2
b0 S
b0 _
#11
b0 d
b0 b
b0 z
#16
bz n
bz !
bz 1
bz 4
bz [
bz ^
bz l
bz r
bz x
bz m
0]
00
0j
0i
0@
0:
0I
b0z0010000000000000000x00zzz "
0H
0#
#24
b10001000000100001 Y
b10001000000100001 T
b10001000000100001 W
b10001000000100001 y
1Z
1V
1P
b10 O
1=
1D
b100z0010000000000100001x00zzz "
1E
1#
#25
b10001000000100001 !
b10001000000100001 1
b10001000000100001 4
b10001000000100001 [
b10001000000100001 ^
b10001000000100001 l
b10001000000100001 r
b10001000000100001 x
b10001000000100001 X
#26
b0 t
b0 !"
b100001 .
b10 ~
b1 }
b0 |
b1000000100001 &"
b10001000000100001 G
b10001000000100001 7
b10001000000100001 \
b10001000000100001 %"
#27
b10001000000100001 d
b10001000000100001 b
b10001000000100001 z
#32
bz !
bz 1
bz 4
bz [
bz ^
bz l
bz r
bz x
bz X
0V
0P
0Z
0D
0E
b0z0010000000000000000x00zzz "
0=
0#
#40
b1 '"
b1 !
b1 1
b1 4
b1 [
b1 ^
b1 l
b1 r
b1 x
b0 ("
b1 &"
13
1#"
1""
b10 $"
b11 O
1;
1?
1>
b11z0010001000000000000x10zzz "
b10 <
1#
#42
06
b1 )
b1 *
b11z0010001000000000000010zzz "
0+
b1 '
b1 5
#43
b1 d
b1 b
b1 z
#48
b1000000100001 &"
bz '"
bz !
bz 1
bz 4
bz [
bz ^
bz l
bz r
bz x
bz ("
03
b0 $"
0#"
0""
0;
b0 <
0?
b0z0010000000000000000000zzz "
0>
0#
#56
1k
1%
b100 O
1J
b1000z0010000100000000000000zzz "
18
1#
#57
b1 `
b1 !
b1 1
b1 4
b1 [
b1 ^
b1 l
b1 r
b1 x
b1 ,
#58
b1 o
#64
bz `
bz !
bz 1
bz 4
bz [
bz ^
bz l
bz r
bz x
bz ,
0%
0k
08
b0z0010000000000000000000zzz "
0J
0#
#72
10
1q
b101 O
1:
b0z0010010010000000000000zzz "
1K
1#
#74
b0 !
b0 1
b0 4
b0 [
b0 ^
b0 l
b0 r
b0 x
b0 u
#75
b0 d
b0 b
b0 z
#80
bz !
bz 1
bz 4
bz [
bz ^
bz l
bz r
bz x
bz u
0q
00
0K
b0z0010000000000000000000zzz "
0:
0#
#88
b1 t
b1 !"
13
1q
b1 {
b110 O
1;
1K
b0z0010001010010000000000zzz "
b1 L
1#
#90
b1 !
b1 1
b1 4
b1 [
b1 ^
b1 l
b1 r
b1 x
b1 u
#91
b1 d
b1 b
b1 z
#96
b0 t
b0 !"
bz !
bz 1
bz 4
bz [
bz ^
bz l
bz r
bz x
bz u
b0 {
0q
03
b0 L
0K
b0z0010000000000000000000zzz "
0;
0#
#104
b101 &
b10 t
b10 !"
b101 /
1s
b10 {
1%
b10 -
b0 O
b0 G
1M
b10 L
18
b0z1010100101100000000000zzz "
b10 9
1#
#105
b1 `
b1 !
b1 1
b1 4
b1 [
b1 ^
b1 l
b1 r
b1 x
b1 ,
#112
bz `
b100 &
b0 t
b0 !"
bz !
bz 1
bz 4
bz [
bz ^
bz l
bz r
bz x
bz ,
b100 /
b0 {
0s
0%
b0 -
b0 L
0M
08
b0z0010000000000000000000zzz "
b0 9
b11000 $
0#
#120
b1 n
b1 !
b1 1
b1 4
b1 [
b1 ^
b1 l
b1 r
b1 x
b0 m
10
1]
1j
1i
b1 O
1:
1@
1I
b110000z0010010000001000000000zzz "
1H
1#
#122
b10 )
b10 *
b1 (
b1 2
b1 S
b1 _
#128
bz n
bz !
bz 1
bz 4
bz [
bz ^
bz l
bz r
bz x
bz m
0]
00
0j
0i
0@
0:
0I
b0z0010000000000000000000zzz "
0H
0#
#136
b100000110010100001100010 Y
b100000110010100001100010 T
b100000110010100001100010 W
b100000110010100001100010 y
1Z
1V
1P
b10 O
1=
1D
b100z0010000000000100001000zzz "
1E
1#
#137
b100000110010100001100010 !
b100000110010100001100010 1
b100000110010100001100010 4
b100000110010100001100010 [
b100000110010100001100010 ^
b100000110010100001100010 l
b100000110010100001100010 r
b100000110010100001100010 x
b100000110010100001100010 X
#138
b100 t
b100 !"
b100010 .
b101 ~
b11 }
b100 |
b10100001100010 &"
b100000110010100001100010 G
b100000110010100001100010 7
b100000110010100001100010 \
b100000110010100001100010 %"
#139
b100000110010100001100010 d
b100000110010100001100010 b
b100000110010100001100010 z
#144
bz !
bz 1
bz 4
bz [
bz ^
bz l
bz r
bz x
bz X
0V
0P
0Z
0D
0E
b0z0010000000000000000000zzz "
0=
0#
#152
b1 '"
b1 !
b1 1
b1 4
b1 [
b1 ^
b1 l
b1 r
b1 x
b0 ("
b1 &"
13
1#"
1""
b10 $"
b11 O
1;
1?
1>
b11z0010001000000000000010zzz "
b10 <
1#
#155
b1 d
b1 b
b1 z
#160
b10100001100010 &"
bz '"
bz !
bz 1
bz 4
bz [
bz ^
bz l
bz r
bz x
bz ("
03
b0 $"
0#"
0""
0;
b0 <
0?
b0z0010000000000000000000zzz "
0>
0#
#168
1k
1%
b100 O
1J
b1000z0010000100000000000000zzz "
18
1#
#169
b10 `
b10 !
b10 1
b10 4
b10 [
b10 ^
b10 l
b10 r
b10 x
b10 ,
#170
b10 o
#171
b10 d
b10 b
b10 z
#176
bz `
bz !
bz 1
bz 4
bz [
bz ^
bz l
bz r
bz x
bz ,
0%
0k
08
b0z0010000000000000000000zzz "
0J
0#
#184
10
1q
b101 O
1:
b0z0010010010000000000000zzz "
1K
1#
#186
b101 )
b101 *
b100 (
b100 2
b100 !
b100 1
b100 4
b100 [
b100 ^
b100 l
b100 r
b100 x
b100 u
#187
b100 d
b100 b
b100 z
#192
bz !
bz 1
bz 4
bz [
bz ^
bz l
bz r
bz x
bz u
0q
00
0K
b0z0010000000000000000000zzz "
0:
0#
#200
b11 t
b11 !"
13
1q
b1 {
b110 O
1;
1K
b0z0010001010010000000000zzz "
b1 L
1#
#202
b111 )
b111 *
b11 '
b11 5
b11 !
b11 1
b11 4
b11 [
b11 ^
b11 l
b11 r
b11 x
b11 u
#203
b11 d
b11 b
b11 z
#208
b100 t
b100 !"
bz !
bz 1
bz 4
bz [
bz ^
bz l
bz r
bz x
bz u
b0 {
0q
03
b0 L
0K
b0z0010000000000000000000zzz "
0;
0#
#216
b1 )
b1 *
b110 &
b101 t
b101 !"
b110 /
1s
b10 {
1%
b10 -
b0 O
b0 G
1M
b10 L
18
b0z1011000101100000000000zzz "
b10 9
1#
